checker/__init__.py
checker/certificate_utils.py
checker/entitlement_utils.py
checker/ocsp_utils.py
async_apple_checker-0.0.1.dist-info/METADATA
async_apple_checker-0.0.1.dist-info/WHEEL
async_apple_checker-0.0.1.dist-info/top_level.txt
async_apple_checker-0.0.1.dist-info/RECORD
