Metadata-Version: 2.4
Name: async-apple-checker
Version: 0.0.1
Summary: A package to check apple related certificates (p12 & mobileprovision) asyncronously.
Home-page: https://github.com/jainamoswal/asycn-apple-checker
Author: jainamoswal
Author-email: me@jainam.me
Classifier: Programming Language :: Python :: 3
Classifier: License :: OSI Approved :: MIT License
Classifier: Operating System :: OS Independent
Requires-Python: >=3.10
Requires-Dist: async-lru>=2.0.5
Requires-Dist: aiohttp>=3.11.16
Requires-Dist: cryptography>=44.0.2
Dynamic: author
Dynamic: author-email
Dynamic: classifier
Dynamic: description
Dynamic: description-content-type
Dynamic: home-page
Dynamic: requires-dist
Dynamic: requires-python
Dynamic: summary
